pytone/__init__.py
pytone/kintone.py
pytone/kintone_file.py
pytone/test.py
zenkPytone-2.0.2.dist-info/METADATA
zenkPytone-2.0.2.dist-info/WHEEL
zenkPytone-2.0.2.dist-info/top_level.txt
zenkPytone-2.0.2.dist-info/RECORD
